Metadata-Version: 2.1
Name: sutra
Version: 0.2.2
Summary: A python package for calculating the removal of microbial organisms in the subsurface
Home-page: https://github.com/KWR-Water/sutra
Author: KWR Water Research Institute
Author-email: martin.korevaar@kwrwater.nl, martin.van.der.schans@kwrwater.nl, steven.ros@kwrwater.nl, alex.hockin@kwrwater.nl
License: MIT
Project-URL: Source, https://github.com/KWR-Water/sutra
Project-URL: Documentation, http://sutra.readthedocs.io/en/latest/
Project-URL: Tracker, https://github.com/KWR-Water/sutra/issues
Project-URL: Help, https://github.com/KWR-Water/sutra/issues
Platform: UNKNOWN
Classifier: Development Status :: 4 - Beta
Classifier: Intended Audience :: Science/Research
Classifier: Intended Audience :: Other Audience
Classifier: License :: OSI Approved :: MIT License
Classifier: Programming Language :: Python :: 3.6
Classifier: Programming Language :: Python :: 3.7
Classifier: Topic :: Scientific/Engineering :: Hydrology
Requires-Python: >=3.7
